QuCoPy/__init__.py
qucopy-0.0.1.dist-info/METADATA
qucopy-0.0.1.dist-info/WHEEL
qucopy-0.0.1.dist-info/licenses/LICENSE
qucopy-0.0.1.dist-info/RECORD
